{
  "project_info": {
    "project_number": "167171896590",
    "project_id": "ajari-noersy",
    "storage_bucket": "ajari-noersy.appspot.com"
  },
  "client": [
    {
      "client_info": {
        "mobilesdk_app_id": "1:167171896590:android:607a4b6f98bf3963c2935f",
        "android_client_info": {
          "package_name": "id.noersy.ajari"
        }
      },
      "oauth_client": [
        {
          "client_id": "167171896590-abq0h8nhn5ghaoo91felh6f7ibdjh1dv.apps.googleusercontent.com",
          "client_type": 1,
          "android_info": {
            "package_name": "id.noersy.ajari",
            "certificate_hash": "d4cfb494c7b5ca0a769d8cd993d17814026428b6"
          }
        },
        {
          "client_id": "167171896590-h03dqstj0hq901njdu7s7575v6cu0d47.apps.googleusercontent.com",
          "client_type": 3
        }
      ],
      "api_key": [
        {
          "current_key": "AIzaSyAFpqwZywZYDBxyGH_QJ3vqQsm5xwpFvds"
        }
      ],
      "services": {
        "appinvite_service": {
          "other_platform_oauth_client": [
            {
              "client_id": "167171896590-h03dqstj0hq901njdu7s7575v6cu0d47.apps.googleusercontent.com",
              "client_type": 3
            }
          ]
        }
      }
    }
  ],
  "configuration_version": "1"
}